littleshelf/__init__.py
little_shelf-0.0.2.dist-info/LICENSE
little_shelf-0.0.2.dist-info/WHEEL
little_shelf-0.0.2.dist-info/METADATA
little_shelf-0.0.2.dist-info/RECORD
