Metadata-Version: 2.1
Name: little-shelf
Version: 0.0.2
Summary: Synchronized dictionaries using Greg Little's 'shelf' CRDT.
License: CC0-1.0
Author: Angelo Gladding
Author-email: angelo@lahacker.net
Requires-Python: >=3.9,<4.0
Classifier: License :: CC0 1.0 Universal (CC0 1.0) Public Domain Dedication
Classifier: Programming Language :: Python :: 3
Classifier: Programming Language :: Python :: 3.9
